{"@context":"http://schema.org","@type":"TVSeries","name":"One Big Interruption","partOfTVSeries":"The Hills","description":"Heidi takes a break from Spencer but finds herself missing him more than she'd like. Lauren has to plan a Teen Vogue dinner but takes a backseat to super-intern Emily from New York.","datePublished":"2012-07-30","partOfSeason":2,"episodeNumber":5,"url":"http://www.mtvplay.tv/shows/511-The+Hills/2/5-One+Big+Interruption","image":"http://images.mtvnn.com/0d4e07005484c73adfc7a95f2e59b89c2/original"}