{"@context":"http://schema.org","@type":"TVSeries","name":"607","partOfTVSeries":"Geordie Shore","description":"James and Gary come to blows which shocks the house and Charlotte’s heart strings are pulled for Gary as she offers him support.  A secret singles trip to the Whitsundays ends in disaster as the boys have an unwitting cock block to look after. ","datePublished":"2013-12-15","partOfSeason":6,"episodeNumber":7,"url":"http://www.mtvplay.tv/shows/1138-Geordie+Shore/6/7-607","image":"http://images.mtvnn.com/074985122022e14f5782d6e43d44d393/original"}