{"@context":"http://schema.org","@type":"TVSeries","name":"Crowning Moments","partOfTVSeries":"Awkward","description":"Jenna’s got a new college romance, but can’t escape the high school drama while stage-managing a male beauty pageant. Meanwhile, Tamara grows more desperate in her attempts to win Jake back.","datePublished":"2014-06-01","partOfSeason":4,"episodeNumber":6,"url":"http://www.mtvplay.tv/shows/977-Awkward/4/6-Crowning+Moments","image":"http://images.mtvnn.com/df819c9c6ab98cda0eb01e0ecab2b500/original"}