{"@context":"http://schema.org","@type":"TVSeries","name":"April and Kenny","partOfTVSeries":"Engaged & Underage","description":"April is an 18-year-old, straight-laced good girl determined to walk down the aisle with 22-year-old Kenny, a reformed bad boy who captured her heart. When they met three years ago, Kenny was directionless and abusing drugs and alcohol. Since then, he has","datePublished":"2013-06-03","partOfSeason":2,"episodeNumber":4,"url":"http://www.mtvplay.tv/shows/284-Engaged+&+Underage/2/4-April+and+Kenny","image":"http://images.mtvnn.com/e1f7939ac8eab5ca2602b6fa5c89877f1/original"}