{"@context":"http://schema.org","@type":"TVSeries","name":"Timmy & Eliza","partOfTVSeries":"Say It In Song","description":"​​​In the season premiere of \"Say It In Song\"​, Redfoo helps out Timmy, a restaurant worker that wants to suprise his co-workers with a shocking career change, and Eliza, a dedicated friend who's determined to set up buddy Drew with her BFF.","datePublished":"2015-09-01","partOfSeason":1,"episodeNumber":1,"url":"http://www.mtvplay.tv/shows/2382-Say+It+In+Song/1/1-Timmy+&+Eliza","image":"http://images.mtvnn.com/8b8a461c2a7b133a305e63429845aa05/original"}