{"@context":"http://schema.org","@type":"TVSeries","name":"Chanel and Sterling XX","partOfTVSeries":"Ridiculousness","description":"On an all-new episode of Ridiculousness, Rob, Stee-Lo, and Chanel get their thrills at “Crappyland,” meet some “Secret Aliens,” and experience the joys of having their first “Naturegasm.”","datePublished":"2015-08-23","partOfSeason":6,"episodeNumber":22,"url":"http://www.mtvplay.tv/shows/1080-Ridiculousness/6/22-Chanel+and+Sterling+XX","image":"http://images.mtvnn.com/463e10544001968634a6d1580b968310/original"}