{"@context":"http://schema.org","@type":"TVSeries","name":"Folge 149","partOfTVSeries":"Game One","description":"Lego Universe\r\nDas ist der nächste Schritt der Lego-Macher in Richtung Weltherrschaft.\r\n\r\nNeed for Speed: Hot Pursuit\r\nSeit 1994 verzückt uns Need for Speed mit Autospielen aller Art. \r\n\r\nCall of Duty: Black Ops\r\nWir machen den Test!","datePublished":"2015-10-14","partOfSeason":8,"episodeNumber":32,"url":"http://www.mtvplay.tv/shows/308-Game+One/7/32-Folge+149","image":"http://images.mtvnn.com/3445d1bdd34a6a6a18e1e4bbed6385580/original"}