{"@context":"http://schema.org","@type":"TVSeries","name":"1986 Oldsmobile Cutlass Supreme","partOfTVSeries":"Pimp My Ride","description":"In this episode, the team pimps Logan's Oldsmobile Cutlass Supreme. Logan rolled home with a basketball court floor and a two-toned paint job.","datePublished":"2014-07-06","partOfSeason":1,"episodeNumber":3,"url":"http://www.mtvplay.tv/shows/428-Pimp+My+Ride/1/3-1986+Oldsmobile+Cutlass+Supreme","image":"http://images.mtvnn.com/abcdeafddbc2a19cb29032a3a653d4200/original"}