{"@context":"http://schema.org","@type":"TVSeries","name":"Pick Me, Choose Me, Love Me","partOfTVSeries":"Awkward","description":"In the aftermath of releasing her blog, everyone seems to have an opinion about Jenna’s life. But while everyone else is in it for the entertainment, Jake and Matty want answers.","datePublished":"2012-11-11","partOfSeason":2,"episodeNumber":10,"url":"http://www.mtvplay.tv/shows/977-Awkward/2/10-Pick+Me,+Choose+Me,+Love+Me","image":"http://images.mtvnn.com/15479cd689c82d7fef9c4d70b69ab35a0/original"}