{"@context":"http://schema.org","@type":"TVSeries","name":"Jordan","partOfTVSeries":"16 & Pregnant","description":"17-year-old Jordan is pregnant. Her identical twin sister Jessica has a hard time adjusting to this, and the fact that Jordan's boyfriend Brian takes up most of her time. Noah James was born July 2010, the family is welcoming another baby later this year.","datePublished":"2012-02-28","partOfSeason":3,"episodeNumber":1,"url":"http://www.mtvplay.tv/shows/195-16+&+Pregnant/3/1-Jordan","image":"http://images.mtvnn.com/d03531ccb40960180a52fe65a79b94df2/original"}