{"@context":"http://schema.org","@type":"TVSeries","name":"French Montana","partOfTVSeries":"Ridiculousness","description":"On an all-new episode of Ridiculousness, rapper French Montana serves up some “Smack and Cheese,” avoids dangerous “Gas Assassins,” and learns the true meaning of “Beast Friends Forever.”","datePublished":"2014-10-26","partOfSeason":5,"episodeNumber":12,"url":"http://www.mtvplay.tv/shows/1080-Ridiculousness/5/12-French+Montana","image":"http://images.mtvnn.com/3153e47f08a0482dd9861f67a9e13029/original"}