{"@context":"http://schema.org","@type":"TVSeries","name":"James & Amber","partOfTVSeries":"Say It In Song","description":"Redfoo introduces us to James who has a simple message for his best friend Kaitlyn- “Follow Your Dreams”. Kaitlyn’s a talented comedic performer and James thinks that she should pursue a career in the spotlight.","datePublished":"2015-09-06","partOfSeason":1,"episodeNumber":5,"url":"http://www.mtvplay.tv/shows/2382-Say+It+In+Song/1/5-James+&+Amber","image":"http://images.mtvnn.com/54bb1a3f7b882e1727abd68f773b8578/original"}