{"@context":"http://schema.org","@type":"TVSeries","name":"Taking Changes","partOfTVSeries":"Teen Mom 3","description":"Briana pursues a secret relationship, while Alex invites Matt to celebrate Arabella's first birthday. Katie lets Joey take care of Molli for the weekend, and Mackenzie and her parents don't see eye-to-eye.","datePublished":"2014-05-05","partOfSeason":1,"episodeNumber":12,"url":"http://www.mtvplay.tv/shows/1751-Teen+Mom+3/1/12-Taking+Changes","image":"http://images.mtvnn.com/71d35e3276426f0e1115e79d86d997e1/original"}