{"@context":"http://schema.org","@type":"TVSeries","name":"Secrets and Lies","partOfTVSeries":"Teen Mom","description":"Catelynn and Tyler find their high school romance back on the rocks when Catelynn reveals another lie -- and it ruins a visit to their adoption agent. Gary dresses up as a bunny for Leah on Easter, but a big fight makes Amber question their engagement. Ma","datePublished":"2013-03-28","partOfSeason":2,"episodeNumber":5,"url":"http://www.mtvplay.tv/shows/495-Teen+Mom/2/5-Secrets+and+Lies","image":"http://images.mtvnn.com/132c5cdd749f05e442bb49302b25c9610/original"}