{"@context":"http://schema.org","@type":"TVSeries","name":"Elijah and Ashley / Rebecca and Mo ","partOfTVSeries":"Young & Married ","description":"Rebecca and Mohammed’s daughter arrived just 8 months after they met, which didn’t sit well with their families. Now they are getting married, but with just weeks to go nothing’s been organised. Mo’s family are also upset by their choice of wedding date.","datePublished":"2013-05-05","partOfSeason":1,"episodeNumber":10,"url":"http://www.mtvplay.tv/shows/1533-Young+&+Married+/1/10-Elijah+and+Ashley+/+Rebecca+and+Mo+","image":"http://images.mtvnn.com/d0d18a6ce7df4001f820ec71631eccd10/original"}