{"@context":"http://schema.org","@type":"TVSeries","name":"Friendzone 120 ","partOfTVSeries":"Friendzone","description":"Franklin likes everything about his friend Erica but she doesn’t know that he’s had a crush on her for 5 years. Now he’s ready to open his heart to her. Megan inspires Wayne’s music. Now he wants to reveal his true affections he has for her.","datePublished":"2012-05-14","partOfSeason":1,"episodeNumber":20,"url":"http://www.mtvplay.tv/shows/1084-Friendzone/1/20-Friendzone+120+","image":"http://images.mtvnn.com/97bceea6e7b3c3c916143efb4b634dd50/original"}