{"@context":"http://schema.org","@type":"TVSeries","name":"Lashing Out","partOfTVSeries":"Teen Mom","description":"Catelynn and Tyler find out they will not graduate from high school on time, while Maci tries to work out a visitation schedule with Ryan in spite of being angry about their last encounter.","datePublished":"2013-03-28","partOfSeason":2,"episodeNumber":10,"url":"http://www.mtvplay.tv/shows/495-Teen+Mom/2/10-Lashing+Out","image":"http://images.mtvnn.com/a167bc721f4f2470d6307f2ad817aabc0/original"}